odoo/addons/sale_automatic_workflow_reserve_sale_stock/README.rst
odoo/addons/sale_automatic_workflow_reserve_sale_stock/__init__.py
odoo/addons/sale_automatic_workflow_reserve_sale_stock/__manifest__.py
odoo/addons/sale_automatic_workflow_reserve_sale_stock/i18n/es.po
odoo/addons/sale_automatic_workflow_reserve_sale_stock/i18n/sale_automatic_workflow_reserve_sale_stock.pot
odoo/addons/sale_automatic_workflow_reserve_sale_stock/i18n/sale_automatic_workflow_stock_reserve.pot
odoo/addons/sale_automatic_workflow_reserve_sale_stock/models/__init__.py
odoo/addons/sale_automatic_workflow_reserve_sale_stock/models/automatic_workflow_job.py
odoo/addons/sale_automatic_workflow_reserve_sale_stock/models/sale_workflow_process.py
odoo/addons/sale_automatic_workflow_reserve_sale_stock/readme/CONFIGURE.rst
odoo/addons/sale_automatic_workflow_reserve_sale_stock/readme/CONTRIBUTORS.rst
odoo/addons/sale_automatic_workflow_reserve_sale_stock/readme/DESCRIPTION.rst
odoo/addons/sale_automatic_workflow_reserve_sale_stock/readme/USAGE.rst
odoo/addons/sale_automatic_workflow_reserve_sale_stock/static/description/icon.png
odoo/addons/sale_automatic_workflow_reserve_sale_stock/static/description/index.html
odoo/addons/sale_automatic_workflow_reserve_sale_stock/tests/__init__.py
odoo/addons/sale_automatic_workflow_reserve_sale_stock/tests/test_sale_automatic_workflow_stock_reserve.py
odoo/addons/sale_automatic_workflow_reserve_sale_stock/views/sale_workflow_process_view.xml
odoo13_addon_sale_automatic_workflow_reserve_sale_stock-13.0.1.0.1.dev5.dist-info/METADATA
odoo13_addon_sale_automatic_workflow_reserve_sale_stock-13.0.1.0.1.dev5.dist-info/WHEEL
odoo13_addon_sale_automatic_workflow_reserve_sale_stock-13.0.1.0.1.dev5.dist-info/top_level.txt
odoo13_addon_sale_automatic_workflow_reserve_sale_stock-13.0.1.0.1.dev5.dist-info/RECORD
