Metadata-Version: 2.1
Name: odoo13-addon-sale-automatic-workflow-reserve-sale-stock
Version: 13.0.1.0.1.dev5
Summary: Sale Automatic Workflow: Reserve Sale stock
Home-page: https://github.com/OCA/stock-logistics-warehouse
Author: FactorLibre, Tecnativa, Odoo Community Association (OCA)
Author-email: support@odoo-community.org
License: AGPL-3
Platform: UNKNOWN
Classifier: Programming Language :: Python
Classifier: Framework :: Odoo
Classifier: Framework :: Odoo :: 13.0
Classifier: License :: OSI Approved :: GNU Affero General Public License v3
Requires-Python: >=3.5
Requires-Dist: odoo13-addon-sale-automatic-workflow
Requires-Dist: odoo13-addon-stock-reserve-sale
Requires-Dist: odoo <13.1dev,>=13.0a
